gee2drive/__init__.py
gee2drive/bandtypes.py
gee2drive/exp_report.py
gee2drive/export.py
gee2drive/gee2drive.py
gee2drive/idsearch.py
gee2drive/kml2ee.py
gee2drive-0.1.0.dist-info/METADATA
gee2drive-0.1.0.dist-info/RECORD
gee2drive-0.1.0.dist-info/WHEEL
gee2drive-0.1.0.dist-info/entry_points.txt
gee2drive-0.1.0.dist-info/top_level.txt
