Metadata-Version: 2.1
Name: gee2drive
Version: 0.1.0
Summary: Google Earth Engine to Drive Export Manager
Home-page: https://github.com/samapriya/gee2drive
Author: Samapriya Roy
Author-email: samapriya.roy@gmail.com
License: Apache 2.0
Platform: UNKNOWN
Classifier: Development Status :: 3 - Alpha
Classifier: Intended Audience :: Developers
Classifier: Intended Audience :: Science/Research
Classifier: Natural Language :: English
Classifier: License :: OSI Approved :: Apache Software License
Classifier: Programming Language :: Python
Classifier: Programming Language :: Python :: 2.7
Classifier: Programming Language :: Python :: 3.6
Classifier: Programming Language :: Python :: 3.7
Classifier: Operating System :: OS Independent
Classifier: Topic :: Scientific/Engineering :: GIS
Requires-Dist: earthengine-api (>=0.1.191)
Requires-Dist: gitpython (>=2.1.11)
Requires-Dist: pendulum (>=2.0.2)
Requires-Dist: Pygments (>=2.2.0)
Requires-Dist: prettytable (>=0.7.2)
Requires-Dist: shapely (>=1.6.4); platform_system != "Windows"
